UppercaseName/__init__.py
UppercaseName-0.1.0.dist-info/LICENSE
UppercaseName-0.1.0.dist-info/METADATA
UppercaseName-0.1.0.dist-info/WHEEL
UppercaseName-0.1.0.dist-info/top_level.txt
UppercaseName-0.1.0.dist-info/RECORD
