Metadata-Version: 2.1
Name: UppercaseName
Version: 0.1.0
Summary: A small test package to capatalize names!
Home-page: https://replit.com/@AaravGaur/My-First-Package
Author: Aarav Gaur
Author-email: aaravgaurx@gmail.com
License: UNKNOWN
Platform: UNKNOWN
Classifier: Programming Language :: Python :: 3
Classifier: License :: OSI Approved :: MIT License
Classifier: Operating System :: OS Independent
Requires-Python: >=3.5
